wagtail_rps/__init__.py
wagtail_rps/admin.py
wagtail_rps/apps.py
wagtail_rps/models.py
wagtail_rps/tests.py
wagtail_rps/views.py
wagtail_rps/migrations/__init__.py
wagtail_rps/static/wagtailrps/css/style.css
wagtail_rps/static/wagtailrps/images/logo-white.png
wagtail_rps/static/wagtailrps/images/logo.jpg
wagtail_rps/static/wagtailrps/js/admin.js
wagtail_rps/templates/wagtailadmin/admin_base.html
wagtail_rps/templates/wagtailadmin/base.html
wagtail_rps/templates/wagtailadmin/home.html
wagtail_rps/templates/wagtailadmin/login.html
wagtail_rps/templates/wagtailadmin/skeleton.html
wagtail_rps_template-1.2.0.dist-info/METADATA
wagtail_rps_template-1.2.0.dist-info/WHEEL
wagtail_rps_template-1.2.0.dist-info/top_level.txt
wagtail_rps_template-1.2.0.dist-info/RECORD
