Metadata-Version: 2.1
Name: wagtail-rps-template
Version: 1.2.0
Summary: Wagtail Admin customising for red pepper Customer
Home-page: https://github.com/red-pepper-services/wagtail-rps-template
Author: Manuel Schiegg
Author-email: pypi@schiegg.at
License: MIT
Classifier: Development Status :: 4 - Beta
Classifier: Framework :: Wagtail
Classifier: Intended Audience :: Developers
Classifier: License :: OSI Approved :: MIT License
Classifier: Operating System :: OS Independent
Classifier: Programming Language :: Python
